Metadata-Version: 2.1
Name: odoo14-addon-stock-warehouse-flow-release
Version: 14.0.2.0.1
Summary: Warehouse flows integrated with Operation Release
Home-page: https://github.com/OCA/wms
Author: Camptocamp, BCIM, Odoo Community Association (OCA)
Author-email: support@odoo-community.org
License: AGPL-3
Platform: UNKNOWN
Classifier: Programming Language :: Python
Classifier: Framework :: Odoo
Classifier: Framework :: Odoo :: 14.0
Classifier: License :: OSI Approved :: GNU Affero General Public License v3
Classifier: Development Status :: 3 - Alpha
Requires-Python: >=3.6
Requires-Dist: odoo14-addon-stock-available-to-promise-release
Requires-Dist: odoo14-addon-stock-warehouse-flow
Requires-Dist: odoo (<14.1dev,>=14.0a)
